surainvestments_api_wrapper/__init__.py
surainvestments_api_wrapper/base_api.py
surainvestments_api_wrapper-0.1.1.dist-info/METADATA
surainvestments_api_wrapper-0.1.1.dist-info/WHEEL
surainvestments_api_wrapper-0.1.1.dist-info/top_level.txt
surainvestments_api_wrapper-0.1.1.dist-info/RECORD
