Metadata-Version: 2.1
Name: surainvestments_api_wrapper
Version: 0.1.1
Summary: A Python wrapper for the Sura Uruguay Investment API
Home-page: https://github.com/PabloAlaniz/Sura-Investments-API-Wrapper
Author: Pablo Alaniz
Author-email: pablo@culturainteractiva.com
Classifier: Programming Language :: Python :: 3
Classifier: License :: OSI Approved :: MIT License
Classifier: Operating System :: OS Independent
Requires-Dist: requests
